conduit/__init__.py
conduit/cli/__init__.py
conduit/cli/context.py
conduit/cli/global_group.py
conduit/cli/main.py
conduit/cli/progress.py
conduit/commands/__init__.py
conduit/commands/bundle.py
conduit/commands/config.py
conduit/commands/init.py
conduit/commands/keys.py
conduit/commands/lock.py
conduit/commands/pack.py
conduit/commands/unpack.py
conduit/core/__init__.py
conduit/core/bundle.py
conduit/core/commands.py
conduit/core/config.py
conduit/core/constants.py
conduit/core/logging.py
conduit/core/models.py
conduit/core/oci_types.py
conduit/core/types.py
conduit/core/clients/__init__.py
conduit/core/clients/http.py
conduit/core/clients/oci_native.py
conduit/core/clients/registry.py
conduit/core/schemas/__init__.py
conduit/core/schemas/next/__init__.py
conduit/core/schemas/next/config.json
conduit/core/schemas/next/lock.json
conduit/core/schemas/next/manifest.json
conduit/handlers/__init__.py
conduit/handlers/base.py
conduit/handlers/factory.py
conduit/handlers/file.py
conduit/handlers/http.py
conduit/handlers/oci.py
conduit/handlers/pack.py
conduit/security/__init__.py
conduit/security/keys.py
conduit/security/utils.py
conduit/security/signer/__init__.py
conduit/security/signer/base.py
conduit/security/signer/key_based.py
conduit/services/__init__.py
conduit/services/config.py
conduit/services/lock.py
conduit/services/lockfile.py
conduit/services/manifest.py
conduit/services/pack.py
conduit/services/templating.py
conduit/services/unpack.py
conduit/services/validation.py
conduit/services/cache/__init__.py
conduit/services/cache/http_cache.py
conduit/services/cache/metadata.py
conduit/services/cache/resolver.py
conduit/services/cache/storage.py
conduit_cli-0.0.3.dist-info/METADATA
conduit_cli-0.0.3.dist-info/WHEEL
conduit_cli-0.0.3.dist-info/entry_points.txt
conduit_cli-0.0.3.dist-info/licenses/LICENSE
conduit_cli-0.0.3.dist-info/RECORD
