Metadata-Version: 2.4
Name: conduit-cli
Version: 0.0.3
Summary: Conduit: A CLI tool for bundling and distributing software as OCI artifacts
Author-email: wixregiga <kecyojagi@protonmail.com>
License-File: LICENSE
Requires-Python: >=3.11
Requires-Dist: aiofiles>=24.1.0
Requires-Dist: aiohttp>=3.12.7
Requires-Dist: aioresponses>=0.7.8
Requires-Dist: click>=8.2.1
Requires-Dist: cryptography>=45.0.4
Requires-Dist: cyclonedx-python-lib>=10.3.0
Requires-Dist: docker-registry-client>=0.5.2
Requires-Dist: httpx>=0.28.1
Requires-Dist: jinja2>=3.1.6
Requires-Dist: jsonschema>=4.23.0
Requires-Dist: oras==0.2.35
Requires-Dist: packaging>=25.0
Requires-Dist: pydantic>=2.11.5
Requires-Dist: pyyaml>=6.0.2
Requires-Dist: repro-tarfile>=0.2.0
Requires-Dist: requests>=2.32.3
Requires-Dist: rich>=14.0.0
Requires-Dist: sigstore>=1.0.0
